Metadata-Version: 1.1
Name: usageapi
Version: 1.0.0
Summary: Library that implements the endpoints of the Access Stats API
Home-page: http://github.com/scieloorg/processing
Author: Fabio Batalha
Author-email: fabio.batalha@scielo.org
License: UNKNOWN
Platform: UNKNOWN
Classifier: Development Status :: 4 - Beta
Classifier: Intended Audience :: Developers
Classifier: Programming Language :: Python :: 3
